[
  {
    "id": "66609",
    "name": "Xã Phước Hậu",
    "district_id": "1073",
    "district_name": "Huyện Cần Giuộc",
    "province_id": "49",
    "province_name": "Tỉnh Long An",
    "new_id": "21544",
    "new_name": "Xã Phước Lý",
    "new_province_id": "40",
    "new_province_name": "Tỉnh Tây Ninh"
  },
  {
    "id": "132145",
    "name": "Xã Phước Vĩnh Đông",
    "district_id": "1073",
    "district_name": "Huyện Cần Giuộc",
    "province_id": "49",
    "province_name": "Tỉnh Long An",
    "new_id": "22568",
    "new_name": "Xã Tân Tập",
    "new_province_id": "40",
    "new_province_name": "Tỉnh Tây Ninh"
  },
  {
    "id": "197681",
    "name": "Xã Phước Vĩnh Tây",
    "district_id": "1073",
    "district_name": "Huyện Cần Giuộc",
    "province_id": "49",
    "province_name": "Tỉnh Long An",
    "new_id": "22312",
    "new_name": "Xã Phước Vĩnh Tây",
    "new_province_id": "40",
    "new_province_name": "Tỉnh Tây Ninh"
  },
  {
    "id": "263217",
    "name": "Thị Trấn Cần Giuộc",
    "district_id": "1073",
    "district_name": "Huyện Cần Giuộc",
    "province_id": "49",
    "province_name": "Tỉnh Long An",
    "new_id": "22056",
    "new_name": "Xã Cần Giuộc",
    "new_province_id": "40",
    "new_province_name": "Tỉnh Tây Ninh"
  },
  {
    "id": "328753",
    "name": "Xã Đông Thạnh",
    "district_id": "1073",
    "district_name": "Huyện Cần Giuộc",
    "province_id": "49",
    "province_name": "Tỉnh Long An",
    "new_id": "22568",
    "new_name": "Xã Tân Tập",
    "new_province_id": "40",
    "new_province_name": "Tỉnh Tây Ninh"
  },
  {
    "id": "394289",
    "name": "Xã Long An",
    "district_id": "1073",
    "district_name": "Huyện Cần Giuộc",
    "province_id": "49",
    "province_name": "Tỉnh Long An",
    "new_id": "22312",
    "new_name": "Xã Phước Vĩnh Tây",
    "new_province_id": "40",
    "new_province_name": "Tỉnh Tây Ninh"
  },
  {
    "id": "459825",
    "name": "Xã Long Hậu",
    "district_id": "1073",
    "district_name": "Huyện Cần Giuộc",
    "province_id": "49",
    "province_name": "Tỉnh Long An",
    "new_id": "22056",
    "new_name": "Xã Cần Giuộc",
    "new_province_id": "40",
    "new_province_name": "Tỉnh Tây Ninh"
  },
  {
    "id": "525361",
    "name": "Xã Long Phụng",
    "district_id": "1073",
    "district_name": "Huyện Cần Giuộc",
    "province_id": "49",
    "province_name": "Tỉnh Long An",
    "new_id": "22312",
    "new_name": "Xã Phước Vĩnh Tây",
    "new_province_id": "40",
    "new_province_name": "Tỉnh Tây Ninh"
  },
  {
    "id": "590897",
    "name": "Xã Long Thượng",
    "district_id": "1073",
    "district_name": "Huyện Cần Giuộc",
    "province_id": "49",
    "province_name": "Tỉnh Long An",
    "new_id": "21544",
    "new_name": "Xã Phước Lý",
    "new_province_id": "40",
    "new_province_name": "Tỉnh Tây Ninh"
  },
  {
    "id": "656433",
    "name": "Xã Mỹ Lộc",
    "district_id": "1073",
    "district_name": "Huyện Cần Giuộc",
    "province_id": "49",
    "province_name": "Tỉnh Long An",
    "new_id": "21800",
    "new_name": "Xã Mỹ Lộc",
    "new_province_id": "40",
    "new_province_name": "Tỉnh Tây Ninh"
  },
  {
    "id": "721969",
    "name": "Xã Phước Lại",
    "district_id": "1073",
    "district_name": "Huyện Cần Giuộc",
    "province_id": "49",
    "province_name": "Tỉnh Long An",
    "new_id": "22056",
    "new_name": "Xã Cần Giuộc",
    "new_province_id": "40",
    "new_province_name": "Tỉnh Tây Ninh"
  },
  {
    "id": "787505",
    "name": "Xã Phước Lâm",
    "district_id": "1073",
    "district_name": "Huyện Cần Giuộc",
    "province_id": "49",
    "province_name": "Tỉnh Long An",
    "new_id": "21800",
    "new_name": "Xã Mỹ Lộc",
    "new_province_id": "40",
    "new_province_name": "Tỉnh Tây Ninh"
  },
  {
    "id": "853041",
    "name": "Xã Phước Lý",
    "district_id": "1073",
    "district_name": "Huyện Cần Giuộc",
    "province_id": "49",
    "province_name": "Tỉnh Long An",
    "new_id": "21544",
    "new_name": "Xã Phước Lý",
    "new_province_id": "40",
    "new_province_name": "Tỉnh Tây Ninh"
  },
  {
    "id": "984113",
    "name": "Xã Tân Tập",
    "district_id": "1073",
    "district_name": "Huyện Cần Giuộc",
    "province_id": "49",
    "province_name": "Tỉnh Long An",
    "new_id": "22568",
    "new_name": "Xã Tân Tập",
    "new_province_id": "40",
    "new_province_name": "Tỉnh Tây Ninh"
  },
  {
    "id": "1049649",
    "name": "Xã Thuận Thành",
    "district_id": "1073",
    "district_name": "Huyện Cần Giuộc",
    "province_id": "49",
    "province_name": "Tỉnh Long An",
    "new_id": "21800",
    "new_name": "Xã Mỹ Lộc",
    "new_province_id": "40",
    "new_province_name": "Tỉnh Tây Ninh"
  }
]