[
  {
    "id": "66862",
    "name": "Xã Tân Nghĩa",
    "district_id": "1326",
    "district_name": "Huyện Di Linh",
    "province_id": "46",
    "province_name": "Tỉnh Lâm Đồng",
    "new_id": "11294",
    "new_name": "Xã Bảo Thuận",
    "new_province_id": "30",
    "new_province_name": "Tỉnh Lâm Đồng"
  },
  {
    "id": "132398",
    "name": "Xã Hòa Nam",
    "district_id": "1326",
    "district_name": "Huyện Di Linh",
    "province_id": "46",
    "province_name": "Tỉnh Lâm Đồng",
    "new_id": "10782",
    "new_name": "Xã Hòa Bắc",
    "new_province_id": "30",
    "new_province_name": "Tỉnh Lâm Đồng"
  },
  {
    "id": "197934",
    "name": "Thị Trấn Di Linh",
    "district_id": "1326",
    "district_name": "Huyện Di Linh",
    "province_id": "46",
    "province_name": "Tỉnh Lâm Đồng",
    "new_id": "10270",
    "new_name": "Xã Di Linh",
    "new_province_id": "30",
    "new_province_name": "Tỉnh Lâm Đồng"
  },
  {
    "id": "263470",
    "name": "Xã Bảo Thuận",
    "district_id": "1326",
    "district_name": "Huyện Di Linh",
    "province_id": "46",
    "province_name": "Tỉnh Lâm Đồng",
    "new_id": "11294",
    "new_name": "Xã Bảo Thuận",
    "new_province_id": "30",
    "new_province_name": "Tỉnh Lâm Đồng"
  },
  {
    "id": "329006",
    "name": "Xã Đinh Lạc",
    "district_id": "1326",
    "district_name": "Huyện Di Linh",
    "province_id": "46",
    "province_name": "Tỉnh Lâm Đồng",
    "new_id": "11294",
    "new_name": "Xã Bảo Thuận",
    "new_province_id": "30",
    "new_province_name": "Tỉnh Lâm Đồng"
  },
  {
    "id": "394542",
    "name": "Xã Đinh Trang Hòa",
    "district_id": "1326",
    "district_name": "Huyện Di Linh",
    "province_id": "46",
    "province_name": "Tỉnh Lâm Đồng",
    "new_id": "10526",
    "new_name": "Xã Hòa Ninh",
    "new_province_id": "30",
    "new_province_name": "Tỉnh Lâm Đồng"
  },
  {
    "id": "460078",
    "name": "Xã Gia Hiệp",
    "district_id": "1326",
    "district_name": "Huyện Di Linh",
    "province_id": "46",
    "province_name": "Tỉnh Lâm Đồng",
    "new_id": "11806",
    "new_name": "Xã Gia Hiệp",
    "new_province_id": "30",
    "new_province_name": "Tỉnh Lâm Đồng"
  },
  {
    "id": "525614",
    "name": "Xã Đinh Trang Thượng",
    "district_id": "1326",
    "district_name": "Huyện Di Linh",
    "province_id": "46",
    "province_name": "Tỉnh Lâm Đồng",
    "new_id": "11038",
    "new_name": "Xã Đinh Trang Thượng",
    "new_province_id": "30",
    "new_province_name": "Tỉnh Lâm Đồng"
  },
  {
    "id": "591150",
    "name": "Xã Gia Bắc",
    "district_id": "1326",
    "district_name": "Huyện Di Linh",
    "province_id": "46",
    "province_name": "Tỉnh Lâm Đồng",
    "new_id": "11550",
    "new_name": "Xã Sơn Điền",
    "new_province_id": "30",
    "new_province_name": "Tỉnh Lâm Đồng"
  },
  {
    "id": "656686",
    "name": "Xã Gung Ré",
    "district_id": "1326",
    "district_name": "Huyện Di Linh",
    "province_id": "46",
    "province_name": "Tỉnh Lâm Đồng",
    "new_id": "10270",
    "new_name": "Xã Di Linh",
    "new_province_id": "30",
    "new_province_name": "Tỉnh Lâm Đồng"
  },
  {
    "id": "722222",
    "name": "Xã Hòa Bắc",
    "district_id": "1326",
    "district_name": "Huyện Di Linh",
    "province_id": "46",
    "province_name": "Tỉnh Lâm Đồng",
    "new_id": "10782",
    "new_name": "Xã Hòa Bắc",
    "new_province_id": "30",
    "new_province_name": "Tỉnh Lâm Đồng"
  },
  {
    "id": "787758",
    "name": "Xã Hòa Ninh",
    "district_id": "1326",
    "district_name": "Huyện Di Linh",
    "province_id": "46",
    "province_name": "Tỉnh Lâm Đồng",
    "new_id": "10526",
    "new_name": "Xã Hòa Ninh",
    "new_province_id": "30",
    "new_province_name": "Tỉnh Lâm Đồng"
  },
  {
    "id": "853294",
    "name": "Xã Hòa Trung",
    "district_id": "1326",
    "district_name": "Huyện Di Linh",
    "province_id": "46",
    "province_name": "Tỉnh Lâm Đồng",
    "new_id": "10526",
    "new_name": "Xã Hòa Ninh",
    "new_province_id": "30",
    "new_province_name": "Tỉnh Lâm Đồng"
  },
  {
    "id": "918830",
    "name": "Xã Liên Đầm",
    "district_id": "1326",
    "district_name": "Huyện Di Linh",
    "province_id": "46",
    "province_name": "Tỉnh Lâm Đồng",
    "new_id": "10270",
    "new_name": "Xã Di Linh",
    "new_province_id": "30",
    "new_province_name": "Tỉnh Lâm Đồng"
  },
  {
    "id": "984366",
    "name": "Xã Sơn Điền",
    "district_id": "1326",
    "district_name": "Huyện Di Linh",
    "province_id": "46",
    "province_name": "Tỉnh Lâm Đồng",
    "new_id": "11550",
    "new_name": "Xã Sơn Điền",
    "new_province_id": "30",
    "new_province_name": "Tỉnh Lâm Đồng"
  },
  {
    "id": "1049902",
    "name": "Xã Tam Bố",
    "district_id": "1326",
    "district_name": "Huyện Di Linh",
    "province_id": "46",
    "province_name": "Tỉnh Lâm Đồng",
    "new_id": "11806",
    "new_name": "Xã Gia Hiệp",
    "new_province_id": "30",
    "new_province_name": "Tỉnh Lâm Đồng"
  },
  {
    "id": "1115438",
    "name": "Xã Tân Châu",
    "district_id": "1326",
    "district_name": "Huyện Di Linh",
    "province_id": "46",
    "province_name": "Tỉnh Lâm Đồng",
    "new_id": "10270",
    "new_name": "Xã Di Linh",
    "new_province_id": "30",
    "new_province_name": "Tỉnh Lâm Đồng"
  },
  {
    "id": "1180974",
    "name": "Xã Tân Lâm",
    "district_id": "1326",
    "district_name": "Huyện Di Linh",
    "province_id": "46",
    "province_name": "Tỉnh Lâm Đồng",
    "new_id": "11038",
    "new_name": "Xã Đinh Trang Thượng",
    "new_province_id": "30",
    "new_province_name": "Tỉnh Lâm Đồng"
  },
  {
    "id": "1246510",
    "name": "Xã Tân Thượng",
    "district_id": "1326",
    "district_name": "Huyện Di Linh",
    "province_id": "46",
    "province_name": "Tỉnh Lâm Đồng",
    "new_id": "11038",
    "new_name": "Xã Đinh Trang Thượng",
    "new_province_id": "30",
    "new_province_name": "Tỉnh Lâm Đồng"
  }
]