[
  {
    "id": "66888",
    "name": "Xã Đạo Tú",
    "district_id": "1352",
    "district_name": "Huyện Tam Dương",
    "province_id": "72",
    "province_name": "Tỉnh Vĩnh Phúc",
    "new_id": "16419",
    "new_name": "Xã Tam Dương",
    "new_province_id": "35",
    "new_province_name": "Tỉnh Phú Thọ"
  },
  {
    "id": "132424",
    "name": "Xã Đồng Tĩnh",
    "district_id": "1352",
    "district_name": "Huyện Tam Dương",
    "province_id": "72",
    "province_name": "Tỉnh Vĩnh Phúc",
    "new_id": "17187",
    "new_name": "Xã Tam Dương Bắc",
    "new_province_id": "35",
    "new_province_name": "Tỉnh Phú Thọ"
  },
  {
    "id": "197960",
    "name": "Thị Trấn Hợp Hòa",
    "district_id": "1352",
    "district_name": "Huyện Tam Dương",
    "province_id": "72",
    "province_name": "Tỉnh Vĩnh Phúc",
    "new_id": "16419",
    "new_name": "Xã Tam Dương",
    "new_province_id": "35",
    "new_province_name": "Tỉnh Phú Thọ"
  },
  {
    "id": "263496",
    "name": "Xã An Hòa",
    "district_id": "1352",
    "district_name": "Huyện Tam Dương",
    "province_id": "72",
    "province_name": "Tỉnh Vĩnh Phúc",
    "new_id": "16931",
    "new_name": "Xã Hoàng An",
    "new_province_id": "35",
    "new_province_name": "Tỉnh Phú Thọ"
  },
  {
    "id": "329032",
    "name": "Xã Hội Thịnh",
    "district_id": "1352",
    "district_name": "Huyện Tam Dương",
    "province_id": "72",
    "province_name": "Tỉnh Vĩnh Phúc",
    "new_id": "16675",
    "new_name": "Xã Hội Thịnh",
    "new_province_id": "35",
    "new_province_name": "Tỉnh Phú Thọ"
  },
  {
    "id": "394568",
    "name": "Xã Hướng Đạo",
    "district_id": "1352",
    "district_name": "Huyện Tam Dương",
    "province_id": "72",
    "province_name": "Tỉnh Vĩnh Phúc",
    "new_id": "16419",
    "new_name": "Xã Tam Dương",
    "new_province_id": "35",
    "new_province_name": "Tỉnh Phú Thọ"
  },
  {
    "id": "460104",
    "name": "Xã Duy Phiên",
    "district_id": "1352",
    "district_name": "Huyện Tam Dương",
    "province_id": "72",
    "province_name": "Tỉnh Vĩnh Phúc",
    "new_id": "16675",
    "new_name": "Xã Hội Thịnh",
    "new_province_id": "35",
    "new_province_name": "Tỉnh Phú Thọ"
  },
  {
    "id": "525640",
    "name": "Xã Hoàng Đan",
    "district_id": "1352",
    "district_name": "Huyện Tam Dương",
    "province_id": "72",
    "province_name": "Tỉnh Vĩnh Phúc",
    "new_id": "16931",
    "new_name": "Xã Hoàng An",
    "new_province_id": "35",
    "new_province_name": "Tỉnh Phú Thọ"
  },
  {
    "id": "591176",
    "name": "Xã Hoàng Hoa",
    "district_id": "1352",
    "district_name": "Huyện Tam Dương",
    "province_id": "72",
    "province_name": "Tỉnh Vĩnh Phúc",
    "new_id": "17187",
    "new_name": "Xã Tam Dương Bắc",
    "new_province_id": "35",
    "new_province_name": "Tỉnh Phú Thọ"
  },
  {
    "id": "656712",
    "name": "Xã Hoàng Lâu",
    "district_id": "1352",
    "district_name": "Huyện Tam Dương",
    "province_id": "72",
    "province_name": "Tỉnh Vĩnh Phúc",
    "new_id": "16931",
    "new_name": "Xã Hoàng An",
    "new_province_id": "35",
    "new_province_name": "Tỉnh Phú Thọ"
  },
  {
    "id": "722248",
    "name": "Thị Trấn Kim Long",
    "district_id": "1352",
    "district_name": "Huyện Tam Dương",
    "province_id": "72",
    "province_name": "Tỉnh Vĩnh Phúc",
    "new_id": "16419",
    "new_name": "Xã Tam Dương",
    "new_province_id": "35",
    "new_province_name": "Tỉnh Phú Thọ"
  },
  {
    "id": "787784",
    "name": "Xã Thanh Vân",
    "district_id": "1352",
    "district_name": "Huyện Tam Dương",
    "province_id": "72",
    "province_name": "Tỉnh Vĩnh Phúc",
    "new_id": "16675",
    "new_name": "Xã Hội Thịnh",
    "new_province_id": "35",
    "new_province_name": "Tỉnh Phú Thọ"
  }
]