[
  {
    "id": "67113",
    "name": "Xã Tống Phan",
    "district_id": "1577",
    "district_name": "Huyện Phù Cừ",
    "province_id": "41",
    "province_name": "Tỉnh Hưng Yên",
    "new_id": "2587",
    "new_name": "Xã Quang Hưng",
    "new_province_id": "27",
    "new_province_name": "Tỉnh Hưng Yên"
  },
  {
    "id": "132649",
    "name": "Xã Tống Trân",
    "district_id": "1577",
    "district_name": "Huyện Phù Cừ",
    "province_id": "41",
    "province_name": "Tỉnh Hưng Yên",
    "new_id": "3355",
    "new_name": "Xã Tống Trân",
    "new_province_id": "27",
    "new_province_name": "Tỉnh Hưng Yên"
  },
  {
    "id": "198185",
    "name": "Thị Trấn Trần Cao",
    "district_id": "1577",
    "district_name": "Huyện Phù Cừ",
    "province_id": "41",
    "province_name": "Tỉnh Hưng Yên",
    "new_id": "2587",
    "new_name": "Xã Quang Hưng",
    "new_province_id": "27",
    "new_province_name": "Tỉnh Hưng Yên"
  },
  {
    "id": "263721",
    "name": "Xã Đình Cao",
    "district_id": "1577",
    "district_name": "Huyện Phù Cừ",
    "province_id": "41",
    "province_name": "Tỉnh Hưng Yên",
    "new_id": "3099",
    "new_name": "Xã Tiên Tiến",
    "new_province_id": "27",
    "new_province_name": "Tỉnh Hưng Yên"
  },
  {
    "id": "329257",
    "name": "Xã Đoàn Đào",
    "district_id": "1577",
    "district_name": "Huyện Phù Cừ",
    "province_id": "41",
    "province_name": "Tỉnh Hưng Yên",
    "new_id": "2843",
    "new_name": "Xã Đoàn Đào",
    "new_province_id": "27",
    "new_province_name": "Tỉnh Hưng Yên"
  },
  {
    "id": "394793",
    "name": "Xã Minh Hoàng",
    "district_id": "1577",
    "district_name": "Huyện Phù Cừ",
    "province_id": "41",
    "province_name": "Tỉnh Hưng Yên",
    "new_id": "2843",
    "new_name": "Xã Đoàn Đào",
    "new_province_id": "27",
    "new_province_name": "Tỉnh Hưng Yên"
  },
  {
    "id": "460329",
    "name": "Xã Minh Tân",
    "district_id": "1577",
    "district_name": "Huyện Phù Cừ",
    "province_id": "41",
    "province_name": "Tỉnh Hưng Yên",
    "new_id": "2587",
    "new_name": "Xã Quang Hưng",
    "new_province_id": "27",
    "new_province_name": "Tỉnh Hưng Yên"
  },
  {
    "id": "591401",
    "name": "Xã Nguyên Hòa",
    "district_id": "1577",
    "district_name": "Huyện Phù Cừ",
    "province_id": "41",
    "province_name": "Tỉnh Hưng Yên",
    "new_id": "3355",
    "new_name": "Xã Tống Trân",
    "new_province_id": "27",
    "new_province_name": "Tỉnh Hưng Yên"
  },
  {
    "id": "656937",
    "name": "Xã Nhật Quang",
    "district_id": "1577",
    "district_name": "Huyện Phù Cừ",
    "province_id": "41",
    "province_name": "Tỉnh Hưng Yên",
    "new_id": "3099",
    "new_name": "Xã Tiên Tiến",
    "new_province_id": "27",
    "new_province_name": "Tỉnh Hưng Yên"
  },
  {
    "id": "722473",
    "name": "Xã Phan Sào Nam",
    "district_id": "1577",
    "district_name": "Huyện Phù Cừ",
    "province_id": "41",
    "province_name": "Tỉnh Hưng Yên",
    "new_id": "2843",
    "new_name": "Xã Đoàn Đào",
    "new_province_id": "27",
    "new_province_name": "Tỉnh Hưng Yên"
  },
  {
    "id": "788009",
    "name": "Xã Quang Hưng",
    "district_id": "1577",
    "district_name": "Huyện Phù Cừ",
    "province_id": "41",
    "province_name": "Tỉnh Hưng Yên",
    "new_id": "2587",
    "new_name": "Xã Quang Hưng",
    "new_province_id": "27",
    "new_province_name": "Tỉnh Hưng Yên"
  },
  {
    "id": "853545",
    "name": "Xã Tam Đa",
    "district_id": "1577",
    "district_name": "Huyện Phù Cừ",
    "province_id": "41",
    "province_name": "Tỉnh Hưng Yên",
    "new_id": "3355",
    "new_name": "Xã Tống Trân",
    "new_province_id": "27",
    "new_province_name": "Tỉnh Hưng Yên"
  },
  {
    "id": "919081",
    "name": "Xã Tiên Tiến",
    "district_id": "1577",
    "district_name": "Huyện Phù Cừ",
    "province_id": "41",
    "province_name": "Tỉnh Hưng Yên",
    "new_id": "3099",
    "new_name": "Xã Tiên Tiến",
    "new_province_id": "27",
    "new_province_name": "Tỉnh Hưng Yên"
  }
]