[
  {
    "id": "67884",
    "name": "Xã Văn Xuôi",
    "district_id": "2348",
    "district_name": "Huyện Tu Mơ Rông",
    "province_id": "44",
    "province_name": "Tỉnh Kon Tum",
    "new_id": "20260",
    "new_name": "Xã Măng Ri",
    "new_province_id": "36",
    "new_province_name": "Tỉnh Quảng Ngãi"
  },
  {
    "id": "133420",
    "name": "Xã Tê Xăng",
    "district_id": "2348",
    "district_name": "Huyện Tu Mơ Rông",
    "province_id": "44",
    "province_name": "Tỉnh Kon Tum",
    "new_id": "20260",
    "new_name": "Xã Măng Ri",
    "new_province_id": "36",
    "new_province_name": "Tỉnh Quảng Ngãi"
  },
  {
    "id": "198956",
    "name": "Xã Ngọc Yêu",
    "district_id": "2348",
    "district_name": "Huyện Tu Mơ Rông",
    "province_id": "44",
    "province_name": "Tỉnh Kon Tum",
    "new_id": "20260",
    "new_name": "Xã Măng Ri",
    "new_province_id": "36",
    "new_province_name": "Tỉnh Quảng Ngãi"
  },
  {
    "id": "264492",
    "name": "Xã Đắk Rơ Ông",
    "district_id": "2348",
    "district_name": "Huyện Tu Mơ Rông",
    "province_id": "44",
    "province_name": "Tỉnh Kon Tum",
    "new_id": "19748",
    "new_name": "Xã Đăk Tờ Kan",
    "new_province_id": "36",
    "new_province_name": "Tỉnh Quảng Ngãi"
  },
  {
    "id": "330028",
    "name": "Xã Đắk Tờ Kan",
    "district_id": "2348",
    "district_name": "Huyện Tu Mơ Rông",
    "province_id": "44",
    "province_name": "Tỉnh Kon Tum",
    "new_id": "19748",
    "new_name": "Xã Đăk Tờ Kan",
    "new_province_id": "36",
    "new_province_name": "Tỉnh Quảng Ngãi"
  },
  {
    "id": "395564",
    "name": "Xã Đắk Na",
    "district_id": "2348",
    "district_name": "Huyện Tu Mơ Rông",
    "province_id": "44",
    "province_name": "Tỉnh Kon Tum",
    "new_id": "19492",
    "new_name": "Xã Đăk Sao",
    "new_province_id": "36",
    "new_province_name": "Tỉnh Quảng Ngãi"
  },
  {
    "id": "461100",
    "name": "Xã Tu Mơ Rông",
    "district_id": "2348",
    "district_name": "Huyện Tu Mơ Rông",
    "province_id": "44",
    "province_name": "Tỉnh Kon Tum",
    "new_id": "20004",
    "new_name": "Xã Tu Mơ Rông",
    "new_province_id": "36",
    "new_province_name": "Tỉnh Quảng Ngãi"
  },
  {
    "id": "526636",
    "name": "Xã Đắk Hà",
    "district_id": "2348",
    "district_name": "Huyện Tu Mơ Rông",
    "province_id": "44",
    "province_name": "Tỉnh Kon Tum",
    "new_id": "20004",
    "new_name": "Xã Tu Mơ Rông",
    "new_province_id": "36",
    "new_province_name": "Tỉnh Quảng Ngãi"
  },
  {
    "id": "592172",
    "name": "Xã Đắk Sao",
    "district_id": "2348",
    "district_name": "Huyện Tu Mơ Rông",
    "province_id": "44",
    "province_name": "Tỉnh Kon Tum",
    "new_id": "19492",
    "new_name": "Xã Đăk Sao",
    "new_province_id": "36",
    "new_province_name": "Tỉnh Quảng Ngãi"
  },
  {
    "id": "657708",
    "name": "Xã Măng Ri",
    "district_id": "2348",
    "district_name": "Huyện Tu Mơ Rông",
    "province_id": "44",
    "province_name": "Tỉnh Kon Tum",
    "new_id": "20260",
    "new_name": "Xã Măng Ri",
    "new_province_id": "36",
    "new_province_name": "Tỉnh Quảng Ngãi"
  },
  {
    "id": "723244",
    "name": "Xã Ngọc Lây",
    "district_id": "2348",
    "district_name": "Huyện Tu Mơ Rông",
    "province_id": "44",
    "province_name": "Tỉnh Kon Tum",
    "new_id": "20260",
    "new_name": "Xã Măng Ri",
    "new_province_id": "36",
    "new_province_name": "Tỉnh Quảng Ngãi"
  }
]