[
  {
    "id": "65847",
    "name": "Xã Bình Kiến",
    "district_id": "311",
    "district_name": "Thành Phố Tuy Hòa",
    "province_id": "55",
    "province_name": "Tỉnh Phú Yên",
    "new_id": "533",
    "new_name": "Phường Bình Kiến",
    "new_province_id": "21",
    "new_province_name": "Tỉnh Đắk Lắk"
  },
  {
    "id": "196919",
    "name": "Phường 1",
    "district_id": "311",
    "district_name": "Thành Phố Tuy Hòa",
    "province_id": "55",
    "province_name": "Tỉnh Phú Yên",
    "new_id": "25365",
    "new_name": "Phường Tuy Hòa",
    "new_province_id": "21",
    "new_province_name": "Tỉnh Đắk Lắk"
  },
  {
    "id": "262455",
    "name": "Phường 2",
    "district_id": "311",
    "district_name": "Thành Phố Tuy Hòa",
    "province_id": "55",
    "province_name": "Tỉnh Phú Yên",
    "new_id": "25365",
    "new_name": "Phường Tuy Hòa",
    "new_province_id": "21",
    "new_province_name": "Tỉnh Đắk Lắk"
  },
  {
    "id": "393527",
    "name": "Phường 4",
    "district_id": "311",
    "district_name": "Thành Phố Tuy Hòa",
    "province_id": "55",
    "province_name": "Tỉnh Phú Yên",
    "new_id": "25365",
    "new_name": "Phường Tuy Hòa",
    "new_province_id": "21",
    "new_province_name": "Tỉnh Đắk Lắk"
  },
  {
    "id": "459063",
    "name": "Phường 5",
    "district_id": "311",
    "district_name": "Thành Phố Tuy Hòa",
    "province_id": "55",
    "province_name": "Tỉnh Phú Yên",
    "new_id": "25365",
    "new_name": "Phường Tuy Hòa",
    "new_province_id": "21",
    "new_province_name": "Tỉnh Đắk Lắk"
  },
  {
    "id": "590135",
    "name": "Phường 7",
    "district_id": "311",
    "district_name": "Thành Phố Tuy Hòa",
    "province_id": "55",
    "province_name": "Tỉnh Phú Yên",
    "new_id": "25365",
    "new_name": "Phường Tuy Hòa",
    "new_province_id": "21",
    "new_province_name": "Tỉnh Đắk Lắk"
  },
  {
    "id": "721207",
    "name": "Phường 9",
    "district_id": "311",
    "district_name": "Thành Phố Tuy Hòa",
    "province_id": "55",
    "province_name": "Tỉnh Phú Yên",
    "new_id": "533",
    "new_name": "Phường Bình Kiến",
    "new_province_id": "21",
    "new_province_name": "Tỉnh Đắk Lắk"
  },
  {
    "id": "786743",
    "name": "Phường Phú Đông",
    "district_id": "311",
    "district_name": "Thành Phố Tuy Hòa",
    "province_id": "55",
    "province_name": "Tỉnh Phú Yên",
    "new_id": "1813",
    "new_name": "Phường Phú Yên",
    "new_province_id": "21",
    "new_province_name": "Tỉnh Đắk Lắk"
  },
  {
    "id": "852279",
    "name": "Phường Phú Lâm",
    "district_id": "311",
    "district_name": "Thành Phố Tuy Hòa",
    "province_id": "55",
    "province_name": "Tỉnh Phú Yên",
    "new_id": "1813",
    "new_name": "Phường Phú Yên",
    "new_province_id": "21",
    "new_province_name": "Tỉnh Đắk Lắk"
  },
  {
    "id": "917815",
    "name": "Phường Phú Thạnh",
    "district_id": "311",
    "district_name": "Thành Phố Tuy Hòa",
    "province_id": "55",
    "province_name": "Tỉnh Phú Yên",
    "new_id": "1813",
    "new_name": "Phường Phú Yên",
    "new_province_id": "21",
    "new_province_name": "Tỉnh Đắk Lắk"
  },
  {
    "id": "983351",
    "name": "Xã An Phú",
    "district_id": "311",
    "district_name": "Thành Phố Tuy Hòa",
    "province_id": "55",
    "province_name": "Tỉnh Phú Yên",
    "new_id": "533",
    "new_name": "Phường Bình Kiến",
    "new_province_id": "21",
    "new_province_name": "Tỉnh Đắk Lắk"
  },
  {
    "id": "1048887",
    "name": "Xã Hòa Kiến",
    "district_id": "311",
    "district_name": "Thành Phố Tuy Hòa",
    "province_id": "55",
    "province_name": "Tỉnh Phú Yên",
    "new_id": "533",
    "new_name": "Phường Bình Kiến",
    "new_province_id": "21",
    "new_province_name": "Tỉnh Đắk Lắk"
  }
]