[
  {
    "id": "69132",
    "name": "Phường 22",
    "district_id": "3596",
    "district_name": "Quận Bình Thạnh",
    "province_id": "12",
    "province_name": "Thành Phố Hồ Chí Minh",
    "new_id": "23308",
    "new_name": "Phường Thạnh Mỹ Tây",
    "new_province_id": "12",
    "new_province_name": "Thành Phố Hồ Chí Minh"
  },
  {
    "id": "200204",
    "name": "Phường 25",
    "district_id": "3596",
    "district_name": "Quận Bình Thạnh",
    "province_id": "12",
    "province_name": "Thành Phố Hồ Chí Minh",
    "new_id": "23308",
    "new_name": "Phường Thạnh Mỹ Tây",
    "new_province_id": "12",
    "new_province_name": "Thành Phố Hồ Chí Minh"
  },
  {
    "id": "265740",
    "name": "Phường 26",
    "district_id": "3596",
    "district_name": "Quận Bình Thạnh",
    "province_id": "12",
    "province_name": "Thành Phố Hồ Chí Minh",
    "new_id": "22796",
    "new_name": "Phường Bình Thạnh",
    "new_province_id": "12",
    "new_province_name": "Thành Phố Hồ Chí Minh"
  },
  {
    "id": "331276",
    "name": "Phường 27",
    "district_id": "3596",
    "district_name": "Quận Bình Thạnh",
    "province_id": "12",
    "province_name": "Thành Phố Hồ Chí Minh",
    "new_id": "23564",
    "new_name": "Phường Bình Quới",
    "new_province_id": "12",
    "new_province_name": "Thành Phố Hồ Chí Minh"
  },
  {
    "id": "396812",
    "name": "Phường 28",
    "district_id": "3596",
    "district_name": "Quận Bình Thạnh",
    "province_id": "12",
    "province_name": "Thành Phố Hồ Chí Minh",
    "new_id": "23564",
    "new_name": "Phường Bình Quới",
    "new_province_id": "12",
    "new_province_name": "Thành Phố Hồ Chí Minh"
  },
  {
    "id": "527884",
    "name": "Phường 5",
    "district_id": "3596",
    "district_name": "Quận Bình Thạnh",
    "province_id": "12",
    "province_name": "Thành Phố Hồ Chí Minh",
    "new_id": "22540",
    "new_name": "Phường Gia Định",
    "new_province_id": "12",
    "new_province_name": "Thành Phố Hồ Chí Minh"
  },
  {
    "id": "658956",
    "name": "Phường 7",
    "district_id": "3596",
    "district_name": "Quận Bình Thạnh",
    "province_id": "12",
    "province_name": "Thành Phố Hồ Chí Minh",
    "new_id": "22540",
    "new_name": "Phường Gia Định",
    "new_province_id": "12",
    "new_province_name": "Thành Phố Hồ Chí Minh"
  },
  {
    "id": "724492",
    "name": "Phường 17",
    "district_id": "3596",
    "district_name": "Quận Bình Thạnh",
    "province_id": "12",
    "province_name": "Thành Phố Hồ Chí Minh",
    "new_id": "22540",
    "new_name": "Phường Gia Định",
    "new_province_id": "12",
    "new_province_name": "Thành Phố Hồ Chí Minh"
  },
  {
    "id": "790028",
    "name": "Phường 19",
    "district_id": "3596",
    "district_name": "Quận Bình Thạnh",
    "province_id": "12",
    "province_name": "Thành Phố Hồ Chí Minh",
    "new_id": "23308",
    "new_name": "Phường Thạnh Mỹ Tây",
    "new_province_id": "12",
    "new_province_name": "Thành Phố Hồ Chí Minh"
  },
  {
    "id": "855564",
    "name": "Phường 2",
    "district_id": "3596",
    "district_name": "Quận Bình Thạnh",
    "province_id": "12",
    "province_name": "Thành Phố Hồ Chí Minh",
    "new_id": "22540",
    "new_name": "Phường Gia Định",
    "new_province_id": "12",
    "new_province_name": "Thành Phố Hồ Chí Minh"
  },
  {
    "id": "986636",
    "name": "Phường 1",
    "district_id": "3596",
    "district_name": "Quận Bình Thạnh",
    "province_id": "12",
    "province_name": "Thành Phố Hồ Chí Minh",
    "new_id": "22540",
    "new_name": "Phường Gia Định",
    "new_province_id": "12",
    "new_province_name": "Thành Phố Hồ Chí Minh"
  },
  {
    "id": "1052172",
    "name": "Phường 11",
    "district_id": "3596",
    "district_name": "Quận Bình Thạnh",
    "province_id": "12",
    "province_name": "Thành Phố Hồ Chí Minh",
    "new_id": "23052",
    "new_name": "Phường Bình Lợi Trung",
    "new_province_id": "12",
    "new_province_name": "Thành Phố Hồ Chí Minh"
  },
  {
    "id": "1117708",
    "name": "Phường 12",
    "district_id": "3596",
    "district_name": "Quận Bình Thạnh",
    "province_id": "12",
    "province_name": "Thành Phố Hồ Chí Minh",
    "new_id": "22796",
    "new_name": "Phường Bình Thạnh",
    "new_province_id": "12",
    "new_province_name": "Thành Phố Hồ Chí Minh"
  },
  {
    "id": "1183244",
    "name": "Phường 13",
    "district_id": "3596",
    "district_name": "Quận Bình Thạnh",
    "province_id": "12",
    "province_name": "Thành Phố Hồ Chí Minh",
    "new_id": "23052",
    "new_name": "Phường Bình Lợi Trung",
    "new_province_id": "12",
    "new_province_name": "Thành Phố Hồ Chí Minh"
  },
  {
    "id": "1248780",
    "name": "Phường 14",
    "district_id": "3596",
    "district_name": "Quận Bình Thạnh",
    "province_id": "12",
    "province_name": "Thành Phố Hồ Chí Minh",
    "new_id": "22796",
    "new_name": "Phường Bình Thạnh",
    "new_province_id": "12",
    "new_province_name": "Thành Phố Hồ Chí Minh"
  }
]